LICENSE
README.md
bashsnakegame/__init__.py
bashsnakegame/colors.py
bashsnakegame/constants.py
bashsnakegame/game.py
bashsnakegame/main.py
bashsnakegame/terminal_arts.py
bashsnakegame-0.1.2.dist-info/LICENSE
bashsnakegame-0.1.2.dist-info/WHEEL
bashsnakegame-0.1.2.dist-info/METADATA
bashsnakegame-0.1.2.dist-info/RECORD
