Metadata-Version: 2.1
Name: bashsnakegame
Version: 0.1.2
Summary: A Terminal Snake for Terminal Persons
Home-page: https://github.com/sakthiRathinam/gamesortvisualize
License: MIT-LICENSE
Keywords: terminalsnake,terminalsnakepython
Author: sakthiRatnam
Author-email: sakthiratnam050@gmail.com
Requires-Python: >=3.10,<4.0
Classifier: License :: Other/Proprietary License
Classifier: Programming Language :: Python :: 3
Classifier: Programming Language :: Python :: 3.10
Requires-Dist: colorama (>=0.4.5,<0.5.0)
Requires-Dist: pre-commit (>=2.19.0,<3.0.0)
Requires-Dist: pydantic (>=1.9.1,<2.0.0)
Requires-Dist: pytimedinput (>=2.0.1,<3.0.0)
Requires-Dist: rich (>=12.4.4,<13.0.0)
Project-URL: Documentation, https://github.com/sakthiRathinam/gamesortvisualize
Project-URL: Repository, https://github.com/sakthiRathinam/gamesortvisualize
